zero_theme/__init__.py
zero_theme/admin.py
zero_theme/middleware.py
zero_theme/widgets.py
zero_theme/generics/__init__.py
zero_theme/generics/admin.py
zero_theme/generics/models.py
zero_theme/static/css/styles.css
zero_theme/static/css/sweetalert2.min.css
zero_theme/static/fonts/cryptocoins.ttf
zero_theme/static/fonts/cryptocoins.woff
zero_theme/static/fonts/cryptocoins.woff2
zero_theme/static/fonts/fa-brands-400.eot
zero_theme/static/fonts/fa-brands-400.ttf
zero_theme/static/fonts/fa-brands-400.woff
zero_theme/static/fonts/fa-brands-400.woff2
zero_theme/static/fonts/fa-regular-400.eot
zero_theme/static/fonts/fa-regular-400.ttf
zero_theme/static/fonts/fa-regular-400.woff
zero_theme/static/fonts/fa-regular-400.woff2
zero_theme/static/fonts/fa-solid-900.eot
zero_theme/static/fonts/fa-solid-900.ttf
zero_theme/static/fonts/fa-solid-900.woff
zero_theme/static/fonts/fa-solid-900.woff2
zero_theme/static/fonts/tabler-icons.eot
zero_theme/static/fonts/tabler-icons.ttf
zero_theme/static/fonts/tabler-icons.woff
zero_theme/static/fonts/tabler-icons.woff2
zero_theme/static/images/welcome-bg.png
zero_theme/static/img/dark-logo.svg
zero_theme/static/img/down-arrow-dark.svg
zero_theme/static/img/down-arrow-white.svg
zero_theme/static/img/down-arrow.svg
zero_theme/static/img/favicon.png
zero_theme/static/img/light-logo.svg
zero_theme/static/img/user-1.jpg
zero_theme/static/js/apexcharts.min.js
zero_theme/static/js/app.init.js
zero_theme/static/js/app.min.js
zero_theme/static/js/bootstrap.bundle.min.js
zero_theme/static/js/change_list.js
zero_theme/static/js/dashboard.js
zero_theme/static/js/iconify-icon.min.js
zero_theme/static/js/sidebarmenu.js
zero_theme/static/js/simplebar.min.js
zero_theme/static/js/sweet-alert.init.js
zero_theme/static/js/sweetalert2.min.js
zero_theme/static/js/theme.js
zero_theme/static/js/vendor.min.js
zero_theme/static/js/plugins/Chart.extension.js
zero_theme/static/js/plugins/bootstrap-notify.js
zero_theme/static/js/plugins/chartjs.min.js
django_zero_theme-0.1.17.dist-info/LICENSE
django_zero_theme-0.1.17.dist-info/METADATA
django_zero_theme-0.1.17.dist-info/WHEEL
django_zero_theme-0.1.17.dist-info/top_level.txt
django_zero_theme-0.1.17.dist-info/RECORD
