Metadata-Version: 2.1
Name: django-zero-theme
Version: 0.1.17
Summary: A reusable Django app for ...
Home-page: https://github.com/farjanul/django-zero-theme
Author: Farjanul Nayem
Author-email: mr.farjanul@gmail.com
License: MIT License
Project-URL: Source, https://github.com/farjanul/django-zero-theme
Project-URL: Issue Tracker, https://github.com/farjanul/django-zero-theme/issues
Platform: UNKNOWN
Classifier: Framework :: Django
Classifier: Programming Language :: Python :: 3
Classifier: License :: OSI Approved :: MIT License
Classifier: Operating System :: OS Independent
License-File: LICENSE
Requires-Dist: django>=3.2
Requires-Dist: django-import-export>=4.1.1
Provides-Extra: dev
Requires-Dist: pytest; extra == "dev"
Requires-Dist: tox; extra == "dev"
Requires-Dist: black; extra == "dev"
